[
  {
    "question": "Is there a wine glass in the scene?",
    "answer": "yes",
    "type": "binary_predicate",
    "objects_referenced": [
      "wine glass"
    ],
    "image_path": "data/frames/05_production_mp/05_production_mp_f000832.jpg"
  },
  {
    "question": "Are there more people or beds in the scene?",
    "answer": "yes",
    "type": "binary_predicate",
    "objects_referenced": [
      "person",
      "bed"
    ],
    "image_path": "data/frames/05_production_mp/05_production_mp_f000832.jpg"
  },
  {
    "question": "How many cups are visible in the scene?",
    "answer": "2",
    "type": "quantitative_distance",
    "objects_referenced": [
      "cup"
    ],
    "image_path": "data/frames/05_production_mp/05_production_mp_f000832.jpg"
  },
  {
    "question": "How many people are present in the scene?",
    "answer": "3",
    "type": "quantitative_distance",
    "objects_referenced": [
      "person"
    ],
    "image_path": "data/frames/05_production_mp/05_production_mp_f000832.jpg"
  },
  {
    "question": "Is the dining table closer to the camera than the average scene depth?",
    "answer": "no",
    "type": "relative_position",
    "objects_referenced": [
      "dining table"
    ],
    "image_path": "data/frames/05_production_mp/05_production_mp_f000832.jpg"
  },
  {
    "question": "Are the cups positioned near the dining table?",
    "answer": "yes",
    "type": "relative_position",
    "objects_referenced": [
      "cup",
      "dining table"
    ],
    "image_path": "data/frames/05_production_mp/05_production_mp_f000832.jpg"
  },
  {
    "question": "Is the wine glass at a greater distance than 15 metres from the camera?",
    "answer": "yes",
    "type": "quantitative_distance",
    "objects_referenced": [
      "wine glass"
    ],
    "image_path": "data/frames/05_production_mp/05_production_mp_f000832.jpg"
  },
  {
    "question": "Are there any beds in proximity to the dining area?",
    "answer": "no",
    "type": "binary_predicate",
    "objects_referenced": [
      "bed",
      "dining table"
    ],
    "image_path": "data/frames/05_production_mp/05_production_mp_f000832.jpg"
  }
]