[
  {
    "question": "How many people are visible in this scene?",
    "answer": "2",
    "type": "quantitative_distance",
    "objects_referenced": [
      "person",
      "person"
    ],
    "image_path": "data/frames/05_production_mp/05_production_mp_f002006.jpg"
  },
  {
    "question": "Are there any workers present at this construction site?",
    "answer": "yes",
    "type": "binary_predicate",
    "objects_referenced": [
      "person"
    ],
    "image_path": "data/frames/05_production_mp/05_production_mp_f002006.jpg"
  },
  {
    "question": "What is the maximum distance observed in this scene?",
    "answer": "50.00 metres",
    "type": "quantitative_distance",
    "objects_referenced": [
      "person"
    ],
    "image_path": "data/frames/05_production_mp/05_production_mp_f002006.jpg"
  },
  {
    "question": "What is the average depth measurement in this scene?",
    "answer": "18.55 metres",
    "type": "quantitative_distance",
    "objects_referenced": [
      "person"
    ],
    "image_path": "data/frames/05_production_mp/05_production_mp_f002006.jpg"
  },
  {
    "question": "Are the persons positioned at the same depth or different depths?",
    "answer": "Unable to determine from available data",
    "type": "relative_position",
    "objects_referenced": [
      "person",
      "person"
    ],
    "image_path": "data/frames/05_production_mp/05_production_mp_f002006.jpg"
  },
  {
    "question": "Is there any heavy equipment detected near the workers?",
    "answer": "no",
    "type": "safety_alert",
    "objects_referenced": [
      "person"
    ],
    "image_path": "data/frames/05_production_mp/05_production_mp_f002006.jpg"
  }
]