[
  {
    "question": "How many bananas are visible in the scene?",
    "answer": "2",
    "type": "quantitative_distance",
    "objects_referenced": [
      "banana"
    ],
    "image_path": "data/frames/05_production_mp/05_production_mp_f003280.jpg"
  },
  {
    "question": "Is there a person present in the scene?",
    "answer": "yes",
    "type": "binary_predicate",
    "objects_referenced": [
      "person"
    ],
    "image_path": "data/frames/05_production_mp/05_production_mp_f003280.jpg"
  },
  {
    "question": "Are there more bananas than people in the scene?",
    "answer": "yes",
    "type": "binary_predicate",
    "objects_referenced": [
      "banana",
      "person"
    ],
    "image_path": "data/frames/05_production_mp/05_production_mp_f003280.jpg"
  },
  {
    "question": "What is the maximum depth distance in the scene?",
    "answer": "50.00 metres",
    "type": "quantitative_distance",
    "objects_referenced": [
      "banana",
      "person"
    ],
    "image_path": "data/frames/05_production_mp/05_production_mp_f003280.jpg"
  },
  {
    "question": "What is the average depth of objects in the scene?",
    "answer": "15.46 metres",
    "type": "quantitative_distance",
    "objects_referenced": [
      "banana",
      "person"
    ],
    "image_path": "data/frames/05_production_mp/05_production_mp_f003280.jpg"
  },
  {
    "question": "Is the person located closer to the camera than the maximum scene depth?",
    "answer": "yes",
    "type": "binary_predicate",
    "objects_referenced": [
      "person"
    ],
    "image_path": "data/frames/05_production_mp/05_production_mp_f003280.jpg"
  }
]