[
  {
    "question": "Is there a person visible in this scene?",
    "answer": "yes",
    "type": "binary_predicate",
    "objects_referenced": [
      "person"
    ],
    "image_path": "data/frames/06_production_mp/06_production_mp_f001782.jpg"
  },
  {
    "question": "How far away is the person from the camera on average?",
    "answer": "14.77 metres",
    "type": "quantitative_distance",
    "objects_referenced": [
      "person"
    ],
    "image_path": "data/frames/06_production_mp/06_production_mp_f001782.jpg"
  },
  {
    "question": "What is the maximum distance to any object in this scene?",
    "answer": "50.00 metres",
    "type": "quantitative_distance",
    "objects_referenced": [
      "person"
    ],
    "image_path": "data/frames/06_production_mp/06_production_mp_f001782.jpg"
  },
  {
    "question": "Is the person located at the closest point in the scene?",
    "answer": "no",
    "type": "binary_predicate",
    "objects_referenced": [
      "person"
    ],
    "image_path": "data/frames/06_production_mp/06_production_mp_f001782.jpg"
  },
  {
    "question": "What is the minimum recorded depth in this scene?",
    "answer": "0.00 metres",
    "type": "quantitative_distance",
    "objects_referenced": [
      "person"
    ],
    "image_path": "data/frames/06_production_mp/06_production_mp_f001782.jpg"
  }
]