[
  {
    "question": "Are there any workers visible on this construction site?",
    "answer": "no",
    "type": "binary_predicate",
    "objects_referenced": [],
    "image_path": "data/frames/06_production_mp/06_production_mp_f000910.jpg"
  },
  {
    "question": "Is any heavy equipment detected in the scene?",
    "answer": "no",
    "type": "binary_predicate",
    "objects_referenced": [],
    "image_path": "data/frames/06_production_mp/06_production_mp_f000910.jpg"
  },
  {
    "question": "What is the average depth of the scene?",
    "answer": "16.93 metres",
    "type": "quantitative_distance",
    "objects_referenced": [],
    "image_path": "data/frames/06_production_mp/06_production_mp_f000910.jpg"
  },
  {
    "question": "What is the maximum distance visible in this scene?",
    "answer": "50.00 metres",
    "type": "quantitative_distance",
    "objects_referenced": [],
    "image_path": "data/frames/06_production_mp/06_production_mp_f000910.jpg"
  },
  {
    "question": "What is the minimum depth recorded in the scene?",
    "answer": "0.00 metres",
    "type": "quantitative_distance",
    "objects_referenced": [],
    "image_path": "data/frames/06_production_mp/06_production_mp_f000910.jpg"
  },
  {
    "question": "Are there any safety hazards detected based on worker-equipment proximity?",
    "answer": "no",
    "type": "safety_alert",
    "objects_referenced": [],
    "image_path": "data/frames/06_production_mp/06_production_mp_f000910.jpg"
  }
]