[
  {
    "question": "Is there a person visible in this scene?",
    "answer": "yes",
    "type": "binary_predicate",
    "objects_referenced": [
      "person"
    ],
    "image_path": "data/frames/06_production_mp/06_production_mp_f001884.jpg"
  },
  {
    "question": "How far away is the person from the camera on average?",
    "answer": "15.32 metres",
    "type": "quantitative_distance",
    "objects_referenced": [
      "person"
    ],
    "image_path": "data/frames/06_production_mp/06_production_mp_f001884.jpg"
  },
  {
    "question": "What is the maximum distance to any object in this scene?",
    "answer": "50.00 metres",
    "type": "quantitative_distance",
    "objects_referenced": [
      "person"
    ],
    "image_path": "data/frames/06_production_mp/06_production_mp_f001884.jpg"
  },
  {
    "question": "Is the person at the closest point in the scene?",
    "answer": "no",
    "type": "binary_predicate",
    "objects_referenced": [
      "person"
    ],
    "image_path": "data/frames/06_production_mp/06_production_mp_f001884.jpg"
  },
  {
    "question": "How many people are detected in this construction scene?",
    "answer": "1",
    "type": "quantitative_distance",
    "objects_referenced": [
      "person"
    ],
    "image_path": "data/frames/06_production_mp/06_production_mp_f001884.jpg"
  },
  {
    "question": "Is there any safety concern regarding worker proximity to heavy equipment in this scene?",
    "answer": "No heavy equipment detected in proximity to the worker.",
    "type": "safety_alert",
    "objects_referenced": [
      "person"
    ],
    "image_path": "data/frames/06_production_mp/06_production_mp_f001884.jpg"
  }
]