[
  {
    "question": "How many people are present in this scene?",
    "answer": "2",
    "type": "quantitative_distance",
    "objects_referenced": [
      "person"
    ],
    "image_path": "data/frames/06_production_mp/06_production_mp_f000882.jpg"
  },
  {
    "question": "Is there a television in the scene?",
    "answer": "yes",
    "type": "binary_predicate",
    "objects_referenced": [
      "tv"
    ],
    "image_path": "data/frames/06_production_mp/06_production_mp_f000882.jpg"
  },
  {
    "question": "Are scissors visible in this scene?",
    "answer": "yes",
    "type": "binary_predicate",
    "objects_referenced": [
      "scissors"
    ],
    "image_path": "data/frames/06_production_mp/06_production_mp_f000882.jpg"
  },
  {
    "question": "What is the approximate maximum depth distance observed in this scene?",
    "answer": "50.00 metres",
    "type": "quantitative_distance",
    "objects_referenced": [
      "person",
      "tv",
      "scissors"
    ],
    "image_path": "data/frames/06_production_mp/06_production_mp_f000882.jpg"
  },
  {
    "question": "Is the TV positioned closer to the camera than the furthest object?",
    "answer": "yes",
    "type": "binary_predicate",
    "objects_referenced": [
      "tv"
    ],
    "image_path": "data/frames/06_production_mp/06_production_mp_f000882.jpg"
  },
  {
    "question": "What is the mean depth distance across all objects in the scene?",
    "answer": "14.82 metres",
    "type": "quantitative_distance",
    "objects_referenced": [
      "person",
      "tv",
      "scissors"
    ],
    "image_path": "data/frames/06_production_mp/06_production_mp_f000882.jpg"
  }
]